indykite_sdk/__init__.py
indykite_sdk/api_helper.py
indykite_sdk/authorization/__init__.py
indykite_sdk/authorization/is_authorized.py
indykite_sdk/authorization/what_authorized.py
indykite_sdk/authorization/who_authorized.py
indykite_sdk/buf/__init__.py
indykite_sdk/buf/validate/__init__.py
indykite_sdk/buf/validate/expression_pb2.py
indykite_sdk/buf/validate/expression_pb2_grpc.py
indykite_sdk/buf/validate/validate_pb2.py
indykite_sdk/buf/validate/validate_pb2_grpc.py
indykite_sdk/buf/validate/priv/__init__.py
indykite_sdk/buf/validate/priv/private_pb2.py
indykite_sdk/buf/validate/priv/private_pb2_grpc.py
indykite_sdk/config/__init__.py
indykite_sdk/config/app_space.py
indykite_sdk/config/application.py
indykite_sdk/config/application_agent.py
indykite_sdk/config/application_agent_credential.py
indykite_sdk/config/config_node.py
indykite_sdk/config/create_application_with_agent_credentials.py
indykite_sdk/config/customer.py
indykite_sdk/config/service_account.py
indykite_sdk/config/service_account_credential.py
indykite_sdk/gnostic/__init__.py
indykite_sdk/gnostic/discovery/__init__.py
indykite_sdk/gnostic/discovery/v1/__init__.py
indykite_sdk/gnostic/discovery/v1/discovery_pb2.py
indykite_sdk/gnostic/discovery/v1/discovery_pb2_grpc.py
indykite_sdk/gnostic/openapi/__init__.py
indykite_sdk/gnostic/openapi/v2/__init__.py
indykite_sdk/gnostic/openapi/v2/openapiv2_pb2.py
indykite_sdk/gnostic/openapi/v2/openapiv2_pb2_grpc.py
indykite_sdk/gnostic/openapi/v3/__init__.py
indykite_sdk/gnostic/openapi/v3/annotations_pb2.py
indykite_sdk/gnostic/openapi/v3/annotations_pb2_grpc.py
indykite_sdk/gnostic/openapi/v3/openapiv3_pb2.py
indykite_sdk/gnostic/openapi/v3/openapiv3_pb2_grpc.py
indykite_sdk/indykite/__init__.py
indykite_sdk/indykite/auditsink/__init__.py
indykite_sdk/indykite/auditsink/v1beta1/__init__.py
indykite_sdk/indykite/auditsink/v1beta1/ai_pb2.py
indykite_sdk/indykite/auditsink/v1beta1/ai_pb2_grpc.py
indykite_sdk/indykite/auditsink/v1beta1/authorization_pb2.py
indykite_sdk_python-1.61.0.dist-info/licenses/LICENSE
indykite_sdk_python-1.61.0.dist-info/METADATA
indykite_sdk_python-1.61.0.dist-info/WHEEL
indykite_sdk_python-1.61.0.dist-info/top_level.txt
indykite_sdk_python-1.61.0.dist-info/RECORD
