Metadata-Version: 2.4
Name: indykite-sdk-python
Version: 1.61.0
Summary: A python SDK package for Indykite's system (with protobuf)
Home-page: https://github.com/indykite/indykite-sdk-python
Author: Indykite
Author-email: test@indykite.com
License: Apache-2.0
Classifier: Programming Language :: Python :: 3
Classifier: License :: OSI Approved :: Apache Software License
Classifier: Operating System :: OS Independent
Requires-Python: ~=3.11
License-File: LICENSE
Requires-Dist: authlib
Requires-Dist: certifi
Requires-Dist: grpcio
Requires-Dist: google-api-python-client
Requires-Dist: google-cloud-storage
Requires-Dist: protobuf
Dynamic: author
Dynamic: author-email
Dynamic: classifier
Dynamic: description
Dynamic: description-content-type
Dynamic: home-page
Dynamic: license
Dynamic: license-file
Dynamic: requires-dist
Dynamic: requires-python
Dynamic: summary
